pip/__init__.py
pip/__main__.py
pip/__pip-runner__.py
pip/py.typed
pip/_internal/__init__.py
pip/_internal/build_env.py
pip/_internal/cache.py
pip/_internal/configuration.py
pip/_internal/exceptions.py
pip/_internal/main.py
pip/_internal/pyproject.py
pip/_internal/self_outdated_check.py
pip/_internal/wheel_builder.py
pip/_internal/cli/__init__.py
pip/_internal/cli/autocompletion.py
pip/_internal/cli/base_command.py
pip/_internal/cli/cmdoptions.py
pip/_internal/cli/command_context.py
pip/_internal/cli/main.py
pip/_internal/cli/main_parser.py
pip/_internal/cli/parser.py
pip/_internal/cli/progress_bars.py
pip/_internal/cli/req_command.py
pip/_internal/cli/spinners.py
pip/_internal/cli/status_codes.py
pip/_internal/commands/__init__.py
pip/_internal/commands/cache.py
pip/_internal/commands/check.py
pip/_internal/commands/completion.py
pip/_internal/commands/configuration.py
pip/_internal/commands/debug.py
pip/_internal/commands/download.py
pip/_internal/commands/freeze.py
pip/_internal/commands/hash.py
pip/_internal/commands/help.py
pip/_internal/commands/index.py
pip/_internal/commands/inspect.py
pip/_internal/commands/install.py
pip/_internal/commands/list.py
pip/_internal/commands/search.py
pip/_internal/commands/show.py
pip/_internal/commands/uninstall.py
pip/_internal/commands/wheel.py
pip/_internal/distributions/__init__.py
pip/_internal/distributions/base.py
pip/_internal/distributions/installed.py
pip/_internal/distributions/sdist.py
pip/_internal/distributions/wheel.py
pip/_internal/index/__init__.py
pip/_internal/index/collector.py
pip/_internal/index/package_finder.py
pip/_internal/index/sources.py
pip/_internal/locations/__init__.py
pip/_internal/locations/_distutils.py
pip/_internal/locations/_sysconfig.py
pip/_internal/locations/base.py
pip/_internal/metadata/__init__.py
pip/_internal/metadata/_json.py
pip/_internal/metadata/base.py
pip/_internal/metadata/pkg_resources.py
pip/_internal/metadata/importlib/__init__.py
secure_pip-23.1.dev3.dist-info/LICENSE.txt
secure_pip-23.1.dev3.dist-info/METADATA
secure_pip-23.1.dev3.dist-info/WHEEL
secure_pip-23.1.dev3.dist-info/entry_points.txt
secure_pip-23.1.dev3.dist-info/top_level.txt
secure_pip-23.1.dev3.dist-info/RECORD
